max_ard/__init__.py
max_ard/admin.py
max_ard/ard_collection.py
max_ard/base_collections.py
max_ard/commands/__init__.py
max_ard/commands/command.py
max_ard/commands/grid.py
max_ard/commands/order.py
max_ard/commands/select.py
max_ard/commands/storage.py
max_ard/dependency_support/__init__.py
max_ard/dependency_support/azure.py
max_ard/exceptions.py
max_ard/io/__init__.py
max_ard/io/inputs.py
max_ard/io/kml_format.py
max_ard/io/kmz_format.py
max_ard/io/qlr_format.py
max_ard/io/shp_format.py
max_ard/metadata.py
max_ard/monitor.py
max_ard/order.py
max_ard/outputs/kml_format.py
max_ard/outputs/kmz_format.py
max_ard/outputs/qlr_format.py
max_ard/outputs/shp_format.py
max_ard/processing.py
max_ard/select.py
max_ard/session.py
max_ard/storage.py
max_ard-1.7.4.dist-info/METADATA
max_ard-1.7.4.dist-info/WHEEL
max_ard-1.7.4.dist-info/entry_points.txt
max_ard-1.7.4.dist-info/RECORD
